purecpp_dev/__init__.py
purecpp_dev/purecpp_chunks_clean_dev.cpython-312-x86_64-linux-gnu.so
purecpp_dev/purecpp_embed_dev.cpython-312-x86_64-linux-gnu.so
purecpp_dev/purecpp_extract_dev.cpython-312-x86_64-linux-gnu.so
purecpp_dev/purecpp_libs_dev.cpython-312-x86_64-linux-gnu.so
purecpp_dev/purecpp_meta_dev.cpython-312-x86_64-linux-gnu.so
purecpp_dev-0.0.300.dist-info/METADATA
purecpp_dev-0.0.300.dist-info/WHEEL
purecpp_dev-0.0.300.dist-info/top_level.txt
purecpp_dev-0.0.300.dist-info/RECORD
